{"coord": {"lon": 78.1167, "lat": 9.9333}, "weather": [{"id": 804, "main": "Clouds", "description": "overcast clouds", "icon": "04n"}], "base": "stations", "main": {"temp": 27.68, "feels_like": 30.92, "temp_min": 27.68, "temp_max": 27.68, "pressure": 1008, "humidity": 77, "sea_level": 1008, "grnd_level": 991}, "visibility": 4654, "wind": {"speed": 1.06, "deg": 260, "gust": 1.76}, "clouds": {"all": 99}, "dt": 1754582805, "sys": {"country": "IN", "sunrise": 1754527079, "sunset": 1754572122}, "timezone": 19800, "id": 1264521, "name": "Madurai", "cod": 200}